lancer/__init__.py
lancer/entry.py
lancer/utils.py
lancer/fixers/__init__.py
lancer/fixers/comments.py
lancer/fixers/variables.py
lancer/resources/lyrics.txt
lancer/resources/sounds.txt
py_lancer-1.0.0.dist-info/AUTHORS.rst
py_lancer-1.0.0.dist-info/LICENSE.txt
py_lancer-1.0.0.dist-info/METADATA
py_lancer-1.0.0.dist-info/WHEEL
py_lancer-1.0.0.dist-info/entry_points.txt
py_lancer-1.0.0.dist-info/top_level.txt
py_lancer-1.0.0.dist-info/RECORD
