Metadata-Version: 2.1
Name: py-lancer
Version: 1.0.0
Summary: A tool to turn your clean python code into a hideous mess.
Home-page: UNKNOWN
Author: Levi Borodenko
Author-email: Levi.borodenko@gmail.com
License: mit
Project-URL: GitHub, https://github.com/LeviBorodenko/lancer
Platform: any
Classifier: Development Status :: 4 - Beta
Classifier: Programming Language :: Python
Provides-Extra: testing
Requires-Dist: pytest ; extra == 'testing'
Requires-Dist: pytest-cov ; extra == 'testing'
